ndsimulator/__init__.py
ndsimulator/_version.py
ndsimulator/constant.py
ndsimulator/data.py
ndsimulator/ndrun.py
ndsimulator/bias/__init__.py
ndsimulator/bias/gaus.py
ndsimulator/bias/pe.py
ndsimulator/bias/umb.py
ndsimulator/colvars/__init__.py
ndsimulator/colvars/_build.py
ndsimulator/colvars/colvar.py
ndsimulator/colvars/five.py
ndsimulator/colvars/misc.py
ndsimulator/colvars/path.py
ndsimulator/colvars/pytorch.py
ndsimulator/colvars/two.py
ndsimulator/engines/__init__.py
ndsimulator/engines/committor.py
ndsimulator/engines/mc.py
ndsimulator/engines/md.py
ndsimulator/engines/minimize.py
ndsimulator/engines/modify.py
ndsimulator/engines/read_dump.py
ndsimulator/engines/wang_landau.py
ndsimulator/interface/__init__.py
ndsimulator/interface/tensorflow/__init__.py
ndsimulator/interface/tensorflow/colvar.py
ndsimulator/io/__init__.py
ndsimulator/io/dump.py
ndsimulator/io/plot.py
ndsimulator/io/stat.py
ndsimulator/potentials/__init__.py
ndsimulator/potentials/_build.py
ndsimulator/potentials/double_well.py
ndsimulator/potentials/flat.py
ndsimulator/potentials/misc.py
ndsimulator/potentials/mueller.py
ndsimulator/potentials/potential.py
ndsimulator/potentials/three_hole.py
ndsimulator/scripts/__init__.py
ndsimulator/scripts/plot_pot.py
ndsimulator/scripts/run.py
ndsimulator-1.1.7.dist-info/LICENSE
ndsimulator-1.1.7.dist-info/METADATA
ndsimulator-1.1.7.dist-info/WHEEL
ndsimulator-1.1.7.dist-info/entry_points.txt
ndsimulator-1.1.7.dist-info/top_level.txt
ndsimulator-1.1.7.dist-info/zip-safe
ndsimulator-1.1.7.dist-info/RECORD
